MANIFEST.in
README.md
setup.cfg
setup.py
docassemble/__init__.py
docassemble.MAVirtualCourt.egg-info/PKG-INFO
docassemble.MAVirtualCourt.egg-info/SOURCES.txt
docassemble.MAVirtualCourt.egg-info/dependency_links.txt
docassemble.MAVirtualCourt.egg-info/namespace_packages.txt
docassemble.MAVirtualCourt.egg-info/not-zip-safe
docassemble.MAVirtualCourt.egg-info/requires.txt
docassemble.MAVirtualCourt.egg-info/top_level.txt
docassemble/MAVirtualCourt/__init__.py
docassemble/MAVirtualCourt/formatting.py
docassemble/MAVirtualCourt/icon.py
docassemble/MAVirtualCourt/phone.py
docassemble/MAVirtualCourt/upload.py
docassemble/MAVirtualCourt/virtual_court_support.py
docassemble/MAVirtualCourt/data/questions/209a_package.yml
docassemble/MAVirtualCourt/data/questions/basic-questions.yml
docassemble/MAVirtualCourt/data/questions/basic_questions_tests.yml
docassemble/MAVirtualCourt/data/questions/cover-page.yml
docassemble/MAVirtualCourt/data/questions/escape.yml
docassemble/MAVirtualCourt/data/questions/feedback.yml
docassemble/MAVirtualCourt/data/questions/form-actions.yml
docassemble/MAVirtualCourt/data/questions/housing_Temporary_Restraining_Order.yml
docassemble/MAVirtualCourt/data/questions/submission.yml
docassemble/MAVirtualCourt/data/sources/README.md
docassemble/MAVirtualCourt/data/sources/court_emails.yml
docassemble/MAVirtualCourt/data/static/README.md
docassemble/MAVirtualCourt/data/static/bug.svg
docassemble/MAVirtualCourt/data/static/colors.css
docassemble/MAVirtualCourt/data/static/confusion.svg
docassemble/MAVirtualCourt/data/static/enhance.svg
docassemble/MAVirtualCourt/data/static/escape.css
docassemble/MAVirtualCourt/data/static/escape.js
docassemble/MAVirtualCourt/data/static/lifebuoy.svg
docassemble/MAVirtualCourt/data/static/love.svg
docassemble/MAVirtualCourt/data/static/mass_icon.png
docassemble/MAVirtualCourt/data/static/opinion.svg
docassemble/MAVirtualCourt/data/static/show_id.js
docassemble/MAVirtualCourt/data/templates/README.md
docassemble/MAVirtualCourt/data/templates/general_cover_sheet.docx