Metadata-Version: 2.1
Name: docassemble.MAVirtualCourt
Version: 1.0.22
Summary: UNKNOWN
Home-page: https://docassemble.org
Author: Quinten Steenhuis
Author-email: qsteenhuis@suffolk.edu
License: MIT
Platform: UNKNOWN
